orientd/__init__.py
orientd/orientd.py
orientd-0.0.13.dist-info/METADATA
orientd-0.0.13.dist-info/RECORD
orientd-0.0.13.dist-info/WHEEL
orientd-0.0.13.dist-info/top_level.txt
