Metadata-Version: 2.1
Name: orientd
Version: 0.0.13
Summary: Daemon for monitoring orientation commands and controlling servo motors
Home-page: UNKNOWN
Author: Matt Wenger
Author-email: wenger_matthew@hotmail.com
License: UNKNOWN
Platform: UNKNOWN
Classifier: Development Status :: 3 - Alpha
Requires-Dist: flask
